astatine/__init__.py
astatine/py.typed
astatine-0.3.1.dist-info/LICENSE
astatine-0.3.1.dist-info/METADATA
astatine-0.3.1.dist-info/WHEEL
astatine-0.3.1.dist-info/top_level.txt
astatine-0.3.1.dist-info/RECORD
