Metadata-Version: 2.1
Name: astatine
Version: 0.3.1
Summary: Some handy helper functions for Python's AST module.
Home-page: https://github.com/domdfcoding/astatine
Author: Dominic Davis-Foster
Author-email: dominic@davis-foster.co.uk
License: MIT License
Project-URL: Documentation, https://astatine.readthedocs.io/en/latest
Project-URL: Issue Tracker, https://github.com/domdfcoding/astatine/issues
Project-URL: Source Code, https://github.com/domdfcoding/astatine
Keywords: ast
Platform: Windows
Platform: macOS
Platform: Linux
Classifier: Development Status :: 4 - Beta
Classifier: Intended Audience :: Developers
Classifier: License :: OSI Approved :: MIT License
Classifier: Operating System :: OS Independent
Classifier: Programming Language :: Python
Classifier: Programming Language :: Python :: 3 :: Only
Classifier: Programming Language :: Python :: 3.6
Classifier: Programming Language :: Python :: 3.7
Classifier: Programming Language :: Python :: 3.8
Classifier: Programming Language :: Python :: 3.9
Classifier: Programming Language :: Python :: Implementation :: CPython
Classifier: Programming Language :: Python :: Implementation :: PyPy
Classifier: Topic :: Software Development :: Libraries :: Python Modules
Classifier: Typing :: Typed
Requires-Python: >=3.6.1
Requires-Dist: asttokens (>=1.1)
Requires-Dist: domdf-python-tools (>=2.7.0)
